exposurescrawler/__init__.py
exposurescrawler/crawlers/__init__.py
exposurescrawler/crawlers/tableau.py
exposurescrawler/dbt/__init__.py
exposurescrawler/dbt/exposure.py
exposurescrawler/dbt/manifest.py
exposurescrawler/tableau/__init__.py
exposurescrawler/tableau/_custom_sql_graphql_query.txt
exposurescrawler/tableau/_native_sql_graphql_query.txt
exposurescrawler/tableau/graphql_client.py
exposurescrawler/tableau/models.py
exposurescrawler/tableau/rest_client.py
exposurescrawler/utils/__init__.py
exposurescrawler/utils/logger.py
exposurescrawler/utils/query_parsing.py
dbt_exposures_crawler-0.1.5.dist-info/LICENSE
dbt_exposures_crawler-0.1.5.dist-info/METADATA
dbt_exposures_crawler-0.1.5.dist-info/WHEEL
dbt_exposures_crawler-0.1.5.dist-info/top_level.txt
dbt_exposures_crawler-0.1.5.dist-info/RECORD
