Metadata-Version: 2.1
Name: dbt-exposures-crawler
Version: 0.1.5
Summary: Extracts information from different systems and convert them to dbt exposures
Home-page: https://github.com/voi-oss/dbt-exposures-crawler
Author: Voi Technology AB
Author-email: opensource@voiapp.io
License: Apache License, Version 2.0
Platform: UNKNOWN
Classifier: Development Status :: 3 - Alpha
Classifier: Programming Language :: Python :: 3
Classifier: Programming Language :: Python :: 3.8
Classifier: Programming Language :: Python :: 3 :: Only
Requires-Python: >=3.8, <4
License-File: LICENSE
Requires-Dist: click ~=8.0.1
Requires-Dist: python-slugify ~=4.0.1
Requires-Dist: tableauserverclient ~=0.10
